test_plugin/custom_header_plugin.py
custom_header_plugin-0.1.0.dist-info/METADATA
custom_header_plugin-0.1.0.dist-info/WHEEL
custom_header_plugin-0.1.0.dist-info/top_level.txt
custom_header_plugin-0.1.0.dist-info/RECORD
